hello_greetings/__init__.py
hello_greetings/cli.py
hello_greetings-1.4.1.dist-info/licenses/LICENSE
hello_greetings-1.4.1.dist-info/METADATA
hello_greetings-1.4.1.dist-info/WHEEL
hello_greetings-1.4.1.dist-info/entry_points.txt
hello_greetings-1.4.1.dist-info/top_level.txt
hello_greetings-1.4.1.dist-info/RECORD
