Metadata-Version: 2.4
Name: hello-greetings
Version: 1.4.1
Summary: A simple command line tool that greets the user
Home-page: https://github.com/AaronOET/hello-greetings
Author: Aaron Hsu
Author-email: Aaron Hsu <aaronhsu@mail.ntou.edu.tw>
Maintainer-email: Aaron Hsu <aaronhsu@mail.ntou.edu.tw>
License: MIT License
Project-URL: Homepage, https://github.com/AaronOET/hello-greetings
Project-URL: Repository, https://github.com/AaronOET/hello-greetings
Project-URL: Issues, https://github.com/AaronOET/hello-greetings/issues
Project-URL: Changelog, https://github.com/AaronOET/hello-greetings/blob/main/CHANGELOG.md
Keywords: greeting,cli,tool
Classifier: Development Status :: 4 - Beta
Classifier: Intended Audience :: Developers
Classifier: Operating System :: OS Independent
Classifier: Programming Language :: Python :: 3
Classifier: Programming Language :: Python :: 3.9
Classifier: Programming Language :: Python :: 3.10
Classifier: Programming Language :: Python :: 3.11
Classifier: Programming Language :: Python :: 3.12
Classifier: Topic :: Software Development :: Libraries :: Python Modules
Classifier: Topic :: Utilities
Requires-Python: >=3.9
License-File: LICENSE
Dynamic: author
Dynamic: home-page
Dynamic: license-file
Dynamic: requires-python
